CHANGELOG.rst
LICENSE
MANIFEST.in
README.rst
VERSION
setup.py
zconfigparser.py
zconfigparser.egg-info/PKG-INFO
zconfigparser.egg-info/SOURCES.txt
zconfigparser.egg-info/dependency_links.txt
zconfigparser.egg-info/not-zip-safe
zconfigparser.egg-info/requires.txt
zconfigparser.egg-info/top_level.txt